[
  { "name": "Bank of Ceylon" },
  { "name": "People's Bank" },
  { "name": "Commercial Bank of Ceylon" },
  { "name": "Hatton National Bank" },
  { "name": "Sampath Bank" },
  { "name": "National Savings Bank" },
  { "name": "Seylan Bank" },
  { "name": "DFCC Bank" },
  { "name": "Nations Trust Bank" },
  { "name": "Union Bank of Colombo" },
  { "name": "Cargills Bank" },
  { "name": "Amana Bank" },
  { "name": "Standard Chartered Bank Sri Lanka" },
  { "name": "HSBC Sri Lanka" },
  { "name": "Deutsche Bank Sri Lanka" },
  { "name": "CitiBank Sri Lanka" },
  { "name": "Indian Bank Sri Lanka" },
  { "name": "Indian Overseas Bank Sri Lanka" },
  { "name": "State Bank of India Sri Lanka" },
  { "name": "MCB Bank Sri Lanka" }
]
